odoo/addons/easy_massive_translation/README.rst
odoo/addons/easy_massive_translation/__init__.py
odoo/addons/easy_massive_translation/__manifest__.py
odoo/addons/easy_massive_translation/i18n/es.po
odoo/addons/easy_massive_translation/static/description/icon.png
odoo/addons/easy_massive_translation/wizards/__init__.py
odoo/addons/easy_massive_translation/wizards/easy_massive_translation_menus.xml
odoo/addons/easy_massive_translation/wizards/export_massive_translation.py
odoo/addons/easy_massive_translation/wizards/export_massive_translation_view.xml
odoo/addons/easy_massive_translation/wizards/import_massive_translation.py
odoo/addons/easy_massive_translation/wizards/import_massive_translation_view.xml
odoo13_addon_easy_massive_translation-13.0.1.0.0.dist-info/METADATA
odoo13_addon_easy_massive_translation-13.0.1.0.0.dist-info/WHEEL
odoo13_addon_easy_massive_translation-13.0.1.0.0.dist-info/top_level.txt
odoo13_addon_easy_massive_translation-13.0.1.0.0.dist-info/RECORD
